fastapi_jsonrpc/__init__.py
fastapi_jsonrpc/contrib/__init__.py
fastapi_jsonrpc/contrib/sentry/__init__.py
fastapi_jsonrpc/contrib/sentry/http.py
fastapi_jsonrpc/contrib/sentry/integration.py
fastapi_jsonrpc/contrib/sentry/jrpc.py
fastapi_jsonrpc/contrib/sentry/test_utils.py
fastapi_jsonrpc/py.typed
fastapi_jsonrpc-3.4.2.dist-info/LICENSE
fastapi_jsonrpc-3.4.2.dist-info/METADATA
fastapi_jsonrpc-3.4.2.dist-info/WHEEL
fastapi_jsonrpc-3.4.2.dist-info/RECORD
