Metadata-Version: 2.1
Name: fastapi-jsonrpc
Version: 3.4.2
Summary: JSON-RPC server based on fastapi
Home-page: https://github.com/smagafurov/fastapi-jsonrpc
License: MIT
Keywords: json-rpc,asgi,swagger,openapi,fastapi,pydantic,starlette
Author: Sergey Magafurov
Author-email: magafurov@tochka.com
Requires-Python: >=3.9,<4.0
Classifier: License :: OSI Approved :: MIT License
Classifier: Programming Language :: Python :: 3
Classifier: Programming Language :: Python :: 3.9
Classifier: Programming Language :: Python :: 3.10
Classifier: Programming Language :: Python :: 3.11
Requires-Dist: aiojobs (>=1.1.0)
Requires-Dist: fastapi (<0.123)
Requires-Dist: fastapi (>=0.112.4)
Requires-Dist: pydantic (<3.0.0)
Requires-Dist: pydantic (>=2.7.0)
Requires-Dist: starlette (>0.0.0)
Project-URL: Repository, https://github.com/smagafurov/fastapi-jsonrpc
